propscraper/__init__.py
propscraper/propertydataextractor.py
propscraper/propscraper.py
PropScraper-0.0.1.dist-info/METADATA
PropScraper-0.0.1.dist-info/WHEEL
PropScraper-0.0.1.dist-info/top_level.txt
PropScraper-0.0.1.dist-info/RECORD
