Metadata-Version: 2.1
Name: PropScraper
Version: 0.0.1
Summary: Web scraper for real state websites
Home-page: https://bitbucket.org/jfdez/propscraper
Author: Jordi Fernández
Author-email: jordi.feca@gmail.com
License: UNKNOWN
Platform: UNKNOWN
Classifier: Programming Language :: Python :: 3
Classifier: License :: OSI Approved :: GNU Affero General Public License v3
Classifier: Operating System :: OS Independent
Requires-Python: >=3.6
Requires-Dist: requests
Requires-Dist: beautifulsoup4
